zipip/__init__.py
zipip/main.py
zipip-2.0.0.dist-info/METADATA
zipip-2.0.0.dist-info/WHEEL
zipip-2.0.0.dist-info/entry_points.txt
zipip-2.0.0.dist-info/top_level.txt
zipip-2.0.0.dist-info/RECORD
