Metadata-Version: 2.4
Name: zipip
Version: 2.0.0
Summary: A simple, custom Python package manager.
Author-email: strtsnm <strtsnm12@gmail.com>
Project-URL: Homepage, https://github.com/STRTSNM/zipip
Project-URL: Bug Tracker, https://github.com/STRTSNM/zipip/issues
Classifier: Programming Language :: Python :: 3
Classifier: License :: OSI Approved :: MIT License
Classifier: Operating System :: OS Independent
Classifier: Topic :: System :: Software Distribution
Requires-Python: >=3.9
Requires-Dist: requests
Requires-Dist: packaging
Requires-Dist: pypdl
